odoo/addons/stock_warehouse_orderpoint_stock_info/README.rst
odoo/addons/stock_warehouse_orderpoint_stock_info/__init__.py
odoo/addons/stock_warehouse_orderpoint_stock_info/__manifest__.py
odoo/addons/stock_warehouse_orderpoint_stock_info/i18n/ca.po
odoo/addons/stock_warehouse_orderpoint_stock_info/i18n/cs_CZ.po
odoo/addons/stock_warehouse_orderpoint_stock_info/i18n/de.po
odoo/addons/stock_warehouse_orderpoint_stock_info/i18n/el_GR.po
odoo/addons/stock_warehouse_orderpoint_stock_info/i18n/es.po
odoo/addons/stock_warehouse_orderpoint_stock_info/i18n/es_ES.po
odoo/addons/stock_warehouse_orderpoint_stock_info/i18n/es_MX.po
odoo/addons/stock_warehouse_orderpoint_stock_info/i18n/eu.po
odoo/addons/stock_warehouse_orderpoint_stock_info/i18n/fi.po
odoo/addons/stock_warehouse_orderpoint_stock_info/i18n/fr.po
odoo/addons/stock_warehouse_orderpoint_stock_info/i18n/fr_CH.po
odoo/addons/stock_warehouse_orderpoint_stock_info/i18n/fr_FR.po
odoo/addons/stock_warehouse_orderpoint_stock_info/i18n/gl.po
odoo/addons/stock_warehouse_orderpoint_stock_info/i18n/hr.po
odoo/addons/stock_warehouse_orderpoint_stock_info/i18n/hr_HR.po
odoo/addons/stock_warehouse_orderpoint_stock_info/i18n/it.po
odoo/addons/stock_warehouse_orderpoint_stock_info/i18n/nl.po
odoo/addons/stock_warehouse_orderpoint_stock_info/i18n/nl_NL.po
odoo/addons/stock_warehouse_orderpoint_stock_info/i18n/pt.po
odoo/addons/stock_warehouse_orderpoint_stock_info/i18n/pt_BR.po
odoo/addons/stock_warehouse_orderpoint_stock_info/i18n/ro.po
odoo/addons/stock_warehouse_orderpoint_stock_info/i18n/ru.po
odoo/addons/stock_warehouse_orderpoint_stock_info/i18n/sl.po
odoo/addons/stock_warehouse_orderpoint_stock_info/i18n/stock_warehouse_orderpoint_stock_info.pot
odoo/addons/stock_warehouse_orderpoint_stock_info/i18n/tr.po
odoo/addons/stock_warehouse_orderpoint_stock_info/i18n/tr_TR.po
odoo/addons/stock_warehouse_orderpoint_stock_info/i18n/vi_VN.po
odoo/addons/stock_warehouse_orderpoint_stock_info/i18n/zh_CN.po
odoo13_addon_stock_warehouse_orderpoint_stock_info-13.0.1.0.1.dev13.dist-info/METADATA
odoo13_addon_stock_warehouse_orderpoint_stock_info-13.0.1.0.1.dev13.dist-info/WHEEL
odoo13_addon_stock_warehouse_orderpoint_stock_info-13.0.1.0.1.dev13.dist-info/top_level.txt
odoo13_addon_stock_warehouse_orderpoint_stock_info-13.0.1.0.1.dev13.dist-info/RECORD
